autosub/__init__.py
autosub/constants.py
autosub/formatters.py
autosub3-0.1.0.dist-info/LICENSE
autosub3-0.1.0.dist-info/METADATA
autosub3-0.1.0.dist-info/WHEEL
autosub3-0.1.0.dist-info/entry_points.txt
autosub3-0.1.0.dist-info/top_level.txt
autosub3-0.1.0.dist-info/RECORD
