Metadata-Version: 2.1
Name: autosub3
Version: 0.1.0
Summary: Auto-generates subtitles for any video or audio file
Home-page: https://github.com/jiaox99/autosub
Author: jiaox99
Author-email: jiaox99@163.com
License: The MIT License (MIT)
Requires-Dist: google-api-python-client (>=1.4.2)
Requires-Dist: requests (>=2.3.0)
Requires-Dist: pysrt (>=1.0.1)
Requires-Dist: progressbar2 (>=3.34.3)
Requires-Dist: six (>=1.11.0)
